<?xml version="1.0" encoding="utf-8"?>
<edmx:Edmx xmlns:edmx="http://docs.oasis-open.org/odata/ns/edmx" Version="4.0">
  <edmx:Reference Uri="https://oasis-tcs.github.io/odata-vocabularies/vocabularies/Org.OData.Core.V1.xml">
    <edmx:Include Alias="Core" Namespace="Org.OData.Core.V1" />
  </edmx:Reference>
  <edmx:Reference Uri="https://oasis-tcs.github.io/odata-vocabularies/vocabularies/Org.OData.Validation.V1.xml">
    <edmx:Include Alias="Validation" Namespace="Org.OData.Validation.V1" />
  </edmx:Reference>
  <edmx:Reference Uri="https://sap.github.io/odata-vocabularies/vocabularies/Common.xml">
    <edmx:Include Namespace="com.sap.vocabularies.Common.v1" Alias="Common" />
  </edmx:Reference>

  <edmx:DataServices>
    <Schema xmlns="http://docs.oasis-open.org/odata/ns/edm" Namespace="com.sap.vocabularies.PersonalData.v1" Alias="PersonalData">
      <Annotation Term="Core.Description">
        <String>Terms for annotating Personal Data</String>
      </Annotation>
      <Annotation Term="Core.Description" Qualifier="Published">
        <String>2018-01-24 © Copyright 2018 SAP SE. All rights reserved</String>
      </Annotation>
      <Annotation Term="Core.Links">
        <Collection>
          <Record>
            <PropertyValue Property="rel" String="latest-version" />
            <PropertyValue Property="href" String="https://sap.github.io/odata-vocabularies/vocabularies/PersonalData.xml" />
          </Record>
          <Record>
            <PropertyValue Property="rel" String="alternate" />
            <PropertyValue Property="href" String="https://sap.github.io/odata-vocabularies/vocabularies/PersonalData.json" />
          </Record>
          <Record>
            <PropertyValue Property="rel" String="describedby" />
            <PropertyValue Property="href" String="https://github.com/sap/odata-vocabularies/blob/main/vocabularies/PersonalData.md" />
          </Record>
        </Collection>
      </Annotation>
      <Annotation Term="Core.LongDescription">
        <String>
## Definition

Personal Data is any information relating to an identified or identifiable natural person ("data subject"). 

An identifiable natural person is one who can be identified, directly or indirectly, in particular by reference to an identifier such as a name, an identification number, location data, an online identifier, or to one or more factors specific to the physical, physiological, genetic, mental, economic, cultural, or social identity of that natural person.

Personal data can only be processed under certain legal grounds, e.g. explicit consent of the data subject or a contractual obligation.

This vocabulary defines terms specific to the European [General Data Protection Regulation (GDPR)](https://ec.europa.eu/info/law/law-topic/data-protection_en).

Terms for contact and address information are defined in the [Communication vocabulary](Communication.md#).

### References
- [European Commission: Reform of EU data protection rules](https://ec.europa.eu/info/law/law-topic/data-protection/reform_en)
- [European Commission: Rules for business and organisations](https://ec.europa.eu/info/law/law-topic/data-protection/reform/rules-business-and-organisations_en)
- [European Commission: Legal grounds for processing data](https://ec.europa.eu/info/law/law-topic/data-protection/reform/rules-business-and-organisations/legal-grounds-processing-data_en).
       </String>
      </Annotation>

      <Term Name="EntitySemantics" Type="PersonalData.EntitySemanticsType" Nullable="false" AppliesTo="EntitySet">
        <Annotation Term="Core.Description" String="Primary meaning of the entities in the annotated entity set" />
      </Term>
      <Term Name="DataSubjectRole" Type="Edm.String" Nullable="true" AppliesTo="EntitySet">
        <Annotation Term="Core.Description" String="Role of the data subjects in this set (e.g. employee, customer)" />
        <Annotation Term="Core.LongDescription">
          <String>Values are application-specific.
          Can be a static value or a `Path` expression If the role varies per entity</String>
        </Annotation>
      </Term>
      <Term Name="DataSubjectRoleDescription" Type="Edm.String" Nullable="true" AppliesTo="EntitySet">
        <Annotation Term="Core.IsLanguageDependent" />
        <Annotation Term="Core.Description" String="Language-dependent description of the role of the data subjects in this set (e.g. employee, customer)" />
        <Annotation Term="Core.LongDescription">
          <String>Values are application-specific.
          Can be a static value or a `Path` expression If the role varies per entity</String>
        </Annotation>
      </Term>
      <TypeDefinition Name="EntitySemanticsType" UnderlyingType="Edm.String">
        <Annotation Term="Core.Description" String="Primary meaning of the data contained in the annotated entity set" />
        <Annotation Term="Validation.AllowedValues">
          <Collection>
            <Record>
              <PropertyValue Property="Value" String="DataSubject" />
              <Annotation Term="Core.Description">
                <String>Entities describing a data subject (an identified or identifiable natural person), e.g. customer, vendor, employee</String>
              </Annotation>
              <Annotation Term="Core.LongDescription">
                <String>These entities are relevant for audit logging. There are no restrictions on their structure. The properties should be annotated suitably with [FieldSemantics](#FieldSemantics).</String>
              </Annotation>
            </Record>
            <Record>
              <PropertyValue Property="Value" String="DataSubjectDetails" />
              <Annotation Term="Core.Description">
                <String>Entities containing details to a data subject (an identified or identifiable natural person) but not representing data subjects by themselves, e.g. street addresses, email addresses, phone numbers</String>
              </Annotation>
              <Annotation Term="Core.LongDescription">
                <String>These entities are relevant for audit logging. There are no restrictions on their structure. The properties should be annotated suitably with [FieldSemantics](#FieldSemantics).</String>
              </Annotation>
            </Record>
            <Record>
              <PropertyValue Property="Value" String="Other" />
              <Annotation Term="Core.Description">
                <String>Entities containing personal data or references to data subjects but not representing data subjects or data subject details by themselves, e.g. customer quote, customer order, purchase order with involved business partners</String>
              </Annotation>
              <Annotation Term="Core.LongDescription">
                <String>These entities are relevant for audit logging. There are no restrictions on their structure. The properties should be annotated suitably with [FieldSemantics](#FieldSemantics).</String>
              </Annotation>
            </Record>
          </Collection>
        </Annotation>
      </TypeDefinition>

      <Term Name="FieldSemantics" Type="PersonalData.FieldSemanticsType" Nullable="false" AppliesTo="Property">
        <Annotation Term="Core.Description" String="Primary meaning of the personal data contained in the annotated property" />
        <Annotation Term="Core.LongDescription" String="Changes to values of annotated properties are tracked in the audit log. Use this annotation also on fields that are already marked as contact or address data." />
      </Term>
      <TypeDefinition Name="FieldSemanticsType" UnderlyingType="Edm.String">
        <Annotation Term="Core.Description" String="Primary meaning of a data field" />
        <Annotation Term="Validation.AllowedValues">
          <Collection>
            <Record>
              <PropertyValue Property="Value" String="DataSubjectID" />
              <Annotation Term="Core.Description" String="The unique identifier for a data subject" />
            </Record>
            <Record>
              <Annotation Term="Common.Experimental" />
              <PropertyValue Property="Value" String="DataSubjectIDType" />
              <Annotation Term="Core.Description" String="The type of ID identifying the data subject and which is allocated when creating a consent record, e.g. an e-mail address or a phone number." />
            </Record>
            <Record>
              <Annotation Term="Common.Experimental" />
              <PropertyValue Property="Value" String="ConsentID" />
              <Annotation Term="Core.Description" String="The unique identifier for a consent" />
              <Annotation Term="Core.LongDescription">
                <String>A consent is the action of the data subject confirming that 
                the usage of his or her personal data shall be allowed for a given purpose. 
                A consent functionality allows the storage of a consent record in relation 
                to a specific purpose and shows if a data subject has granted, withdrawn, 
                or denied consent.</String>
              </Annotation>
            </Record>
            <Record>
              <Annotation Term="Common.Experimental" />
              <PropertyValue Property="Value" String="PurposeID" />
              <Annotation Term="Core.Description" String="The unique identifier for the purpose of a consent" />
              <Annotation Term="Core.LongDescription">
                <String>The unique identifier for the purpose of processing of personal data. Any processing of personal data is based on specified, explicit, and legitimate purposes and not further processed in a manner that is incompatible with those purposes. The purposes are defined by the data controller or joint data controllers.
                </String>
              </Annotation>
            </Record>
            <Record>
              <PropertyValue Property="Value" String="ContractRelatedID" />
              <Annotation Term="Core.Description" String="The unique identifier for transactional data that is related to a contract that requires processing of personal data" />
              <Annotation Term="Core.LongDescription">
                <String>Examples:

                - Sales Contract ID

                - Purchase Contract ID

                - Service Contract ID
                </String>
              </Annotation>
            </Record>
            <Record>
              <PropertyValue Property="Value" String="LegalEntityID" />
              <Annotation Term="Core.Description" String="The unique identifier of a legal entity" />
              <Annotation Term="Core.LongDescription">
                <String>A legal entity is a corporation, an association, or any other organization of legal capacity, which has statutory rights and responsibilities.</String>
              </Annotation>
              <Annotation Term="Core.Revisions">
                <Collection>
                  <Record>
                    <PropertyValue Property="Kind" EnumMember="Core.RevisionKind/Deprecated" />
                    <PropertyValue Property="Description" String="Deprecated in favor of [`DataControllerID`](#DataControllerID)" />
                  </Record>
                </Collection>
              </Annotation>
            </Record>
            <Record>
              <Annotation Term="Common.Experimental" />
              <PropertyValue Property="Value" String="UserID" />
              <Annotation Term="Core.Description" String="The unique identifier of a user" />
              <Annotation Term="Core.LongDescription">
                <String>A user is an individual who interacts with the services supplied by a system.</String>
              </Annotation>
            </Record>
            <Record>
              <Annotation Term="Common.Experimental" />
              <PropertyValue Property="Value" String="EndOfBusinessDate" />
              <Annotation Term="Core.Description" String="Defines the end of active business and the start of residence time and retention period" />
              <Annotation Term="Core.LongDescription">
                <String>End of business is the point in time when the processing of a set of personal data is no longer required for the active business,
                for example, when a contract is fulfilled. After this has been reached and a customer-defined residence period has passed, the data is blocked and can only be accessed
                by users with special authorizations (for example, tax auditors).
                All fields of type `Edm.Date` or `Edm.DateTimeOffset` on which the end of business determination depends should be annotated.</String>
              </Annotation>
            </Record>
            <Record>
              <Annotation Term="Common.Experimental" />
              <PropertyValue Property="Value" String="DataControllerID" />
              <Annotation Term="Core.Description" String="The unique identifier of a data controller" />
              <Annotation Term="Core.LongDescription">
                <String>The unique identifier of a legal entity which alone or jointly with others determines the purposes and means of the processing of personal data. 
                The Data Controller is fully responsible (and accountable) that data protection and privacy principles (such as purpose limitation or data minimization), defined in the European General Data Protection Regulation (GDPR) or any other data protection legislation, are adhered to when processing personal data. The DataControllerID succeeds the LegalEntityID.</String>
              </Annotation>
            </Record>
            <Record>
              <Annotation Term="Common.Experimental" />
              <PropertyValue Property="Value" String="BlockingDate" />
              <Annotation Term="Core.Description" String="Defines a date that marks when the provider of the data will block these" />
              <Annotation Term="Core.LongDescription">
                <String>Defines a date that marks when the provider of the data will block these. This is the point in time when the processing of a set of personal data is no longer required for the active business, for example, when a contract is fulfilled. After it has been reached, the data is blocked in the source and can only be displayed by users with special authorizations (for example, tax auditors); however, it is not allowed to create/change/copy/follow-up blocked data. Consumers of the data should consider if there is an additional purpose to process the data beyond the defined blocking date.</String>
              </Annotation>
            </Record>
            <Record>
              <Annotation Term="Common.Experimental" />
              <PropertyValue Property="Value" String="EndOfRetentionDate" />
              <Annotation Term="Core.Description" String="Defines the date when the provider destroys the data" />
              <Annotation Term="Core.LongDescription">
                <String>Defines a date that marks when the provider of the data can destroy these. Consumers of the data should consider if there is an additional purpose (or a legal hold) to process the data beyond the defined destruction date.</String>
              </Annotation>
            </Record>
          </Collection>
        </Annotation>
      </TypeDefinition>

      <Term Name="IsPotentiallyPersonal" Type="Core.Tag" Nullable="false" DefaultValue="true" AppliesTo="Property">
        <Annotation Term="Core.Description" String="Property contains potentially personal data" />
        <Annotation Term="Core.LongDescription">
          <String>Property contains potentially personal data. Personal data describes any information which is related to an identified or identifiable natural person (data subject). An identifiable person is one who can be identified, directly or indirectly, in particular by a reference to an identifier such as a name, an identification number, location data, an online identifier, or to one or more factors specific to the physical, physiological, genetic, mental, economic, cultural, or social identity of that natural person. Note: properties annotated with [`FieldSemantics`](#FieldSemantics) need not be additionally annotated with this term.
          </String>
        </Annotation>
      </Term>

      <Term Name="IsPotentiallySensitive" Type="Core.Tag" Nullable="false" DefaultValue="true" AppliesTo="Property">
        <Annotation Term="Core.Description" String="Property contains potentially sensitive personal data" />
        <Annotation Term="Core.LongDescription">
          <String>Property contains potentially sensitive personal data. Sensitive personal data is a category of personal data that needs special handling. The determination which personal data is sensitive may differ for different legal areas or industries. Examples of sensitive personal data:
                      - Special categories of personal data, such as data revealing racial or ethnic origin, political opinions, religious or philosophical beliefs, trade union membership, genetic data, biometric data, data concerning health or sex life or sexual orientation.
                      - Personal data subject to professional secrecy. 
                      - Personal data relating to criminal or administrative offences.
                      - Personal data concerning insurances and bank or credit card accounts.
          </String>
        </Annotation>
      </Term>
    </Schema>
  </edmx:DataServices>
</edmx:Edmx>
