{
  "$Version": "4.0",
  "$Reference": {
    "https://sap.github.io/odata-vocabularies/vocabularies/Common.json": {
      "$Include": [{ "$Namespace": "com.sap.vocabularies.Common.v1", "$Alias": "Common" }]
    }
  },
  "isendofday.sample": {
    "WorkerTimeSheet": {
      "$Kind": "EntityType",
      "WorkingDate": { "$Type": "Edm.Date" },
      "ClockInTime": { "$Type": "Edm.TimeOfDay" },
      "ClockOutTime": { "$Type": "Edm.TimeOfDay", "$Nullable": true },
      "ClockOutMidnight": { "$Type": "Edm.Boolean" }
    },
    "$Annotations": {
      "timezone.sample.WorkerTimeSheet/ClockOutTime": { "@Common.IsEndOfDay": { "$Path": "ClockOutMidnight" } }
    }
  }
}
