<?xml version="1.0" encoding="utf-8"?>
<edmx:Edmx Version="4.0" xmlns:edmx="http://docs.oasis-open.org/odata/ns/edmx">
  <edmx:Reference Uri="https://sap.github.io/odata-vocabularies/vocabularies/Common.xml">
    <edmx:Include Namespace="com.sap.vocabularies.Common.v1" Alias="Common" />
  </edmx:Reference>
  <edmx:Reference Uri="https://sap.github.io/odata-vocabularies/vocabularies/UI.xml">
    <edmx:Include Namespace="com.sap.vocabularies.UI.v1" Alias="UI" />
  </edmx:Reference>
  <edmx:Reference Uri="https://sap.github.io/odata-vocabularies/vocabularies/Analytics.xml">
    <edmx:Include Namespace="com.sap.vocabularies.Analytics.v1" Alias="Analytics" />
  </edmx:Reference>
  <edmx:Reference Uri="/sap/opu/odata/sap/C_CNSLDTNBALANCESHEETQ_CDS/$metadata">
    <edmx:Include Namespace="C_CNSLDTNBALANCESHEETQ_CDS" />
  </edmx:Reference>

  <edmx:DataServices>
    <Schema Namespace="UI.examples" xmlns="http://docs.oasis-open.org/odata/ns/edm" Alias="self">

      <Annotations Target="C_CNSLDTNBALANCESHEETQ_CDS.C_CNSLDTNBALANCESHEETQResult">
        <Annotation Term="Analytics.StructureElement" Qualifier="ClsgFiscalYearAmount">
          <Record>
            <Annotation Term="Common.Label">
              <Apply Function="odata.concat">
                <String>Current Year </String>
                <Path>Parameters/P_FiscalYear</Path>
              </Apply>
            </Annotation>
            <PropertyValue Property="Filter">
              <And>
                <Eq>
                  <Path>FiscalYear</Path>
                  <Path>Parameters/P_FiscalYear</Path>
                </Eq>
                <Eq>
                  <Path>ConsolidationVersion</Path>
                  <Path>Parameters/P_ConsolidationVersion</Path>
                </Eq>
              </And>
            </PropertyValue>
          </Record>
        </Annotation>
        <Annotation Term="Analytics.StructureElement" Qualifier="PrevFiscalYearAmount">
          <Record>
            <Annotation Term="Common.Label">
              <Apply Function="odata.concat">
                <String>Previous Year </String>
                <Path>Parameters/P_PreviousFiscalYear</Path>
              </Apply>
            </Annotation>
            <PropertyValue Property="Filter">
              <And>
                <Eq>
                  <Path>FiscalYear</Path>
                  <Path>Parameters/P_PreviousFiscalYear</Path>
                </Eq>
                <Eq>
                  <Path>ConsolidationVersion</Path>
                  <Path>Parameters/P_ConsolidationVersion</Path>
                </Eq>
              </And>
            </PropertyValue>
          </Record>
        </Annotation>
        <Annotation Term="Analytics.Structure" Qualifier="YearComp">
          <Collection>
            <AnnotationPath>@Analytics.StructureElement#ClsgFiscalYearAmount</AnnotationPath>
            <AnnotationPath>@Analytics.StructureElement#PrevFiscalYearAmount</AnnotationPath>
          </Collection>
        </Annotation>
        <Annotation Term="UI.FieldGroup" Qualifier="Rows">
          <Record Type="UI.FieldGroupDimensions">
            <PropertyValue Property="Data">
              <Collection>
                <Record Type="UI.DataField">
                  <PropertyValue Property="Value" Path="FinancialStatementItem" />
                </Record>
              </Collection>
            </PropertyValue>
          </Record>
        </Annotation>
        <Annotation Term="UI.FieldGroup" Qualifier="Columns1">
          <Record Type="UI.FieldGroupDimensions">
            <PropertyValue Property="Data">
              <Collection>
                <Record Type="UI.DataField">
                  <PropertyValue Property="Value" Path="ConsolidationGroup" />
                </Record>
              </Collection>
            </PropertyValue>
          </Record>
        </Annotation>
        <Annotation Term="UI.FieldGroup" Qualifier="Columns2">
          <Record Type="UI.FieldGroupDimensions">
            <PropertyValue Property="Data">
              <Collection>
                <Record Type="UI.DataField">
                  <PropertyValue Property="Value" Path="ConsolidationUnit" />
                </Record>
              </Collection>
            </PropertyValue>
          </Record>
        </Annotation>
        <Annotation Term="UI.FieldGroup" Qualifier="Measures">
          <Record Type="UI.FieldGroupMeasures">
            <PropertyValue Property="Data">
              <Collection>
                <Record Type="UI.DataField">
                  <PropertyValue Property="Value" Path="AmountInGroupCurrency" />
                </Record>
                <Record Type="UI.DataField">
                  <PropertyValue Property="Value" Path="CnsldtnAdjustmentsAmount" />
                </Record>
              </Collection>
            </PropertyValue>
          </Record>
        </Annotation>
        <Annotation Term="UI.DataGrid">
          <Record>
            <PropertyValue Property="Rows">
              <Collection>
                <Record Type="UI.ReferenceFacet">
                  <PropertyValue Property="Target" AnnotationPath="@UI.FieldGroup#Rows" />
                </Record>
              </Collection>
            </PropertyValue>
            <PropertyValue Property="Columns">
              <Collection>
                <Record Type="UI.ReferenceFacet">
                  <PropertyValue Property="Target" AnnotationPath="@UI.FieldGroup#Columns1" />
                </Record>
                <Record Type="UI.ReferenceFacet">
                  <PropertyValue Property="Target" AnnotationPath="@UI.FieldGroup#Measures" />
                </Record>
                <Record Type="UI.ReferenceFacet">
                  <PropertyValue Property="Target" AnnotationPath="@UI.FieldGroup#Columns2" />
                </Record>
                <Record Type="UI.ReferenceFacet">
                  <PropertyValue Property="Label" String="Year Comparison" />
                  <PropertyValue Property="Target" AnnotationPath="@Analytics.Structure#YearComp" />
                </Record>
              </Collection>
            </PropertyValue>
          </Record>
        </Annotation>
      </Annotations>

    </Schema>
  </edmx:DataServices>
</edmx:Edmx>
